paramfittorchdemo/__init__.py
paramfittorchdemo/_modidx.py
paramfittorchdemo/models.py
paramfittorchdemo/training.py
paramfittorchdemo-0.0.1.dist-info/LICENSE
paramfittorchdemo-0.0.1.dist-info/METADATA
paramfittorchdemo-0.0.1.dist-info/WHEEL
paramfittorchdemo-0.0.1.dist-info/entry_points.txt
paramfittorchdemo-0.0.1.dist-info/top_level.txt
paramfittorchdemo-0.0.1.dist-info/RECORD
