Metadata-Version: 2.1
Name: paramfittorchdemo
Version: 0.0.1
Summary: How to use pytorch to fit parameters of differential equations
Home-page: https://github.com/khannay/paramfittorchdemo
Author: Kevin Hannay
Author-email: 13168556+khannay@users.noreply.github.com
License: Apache Software License 2.0
Keywords: nbdev jupyter notebook python
Platform: UNKNOWN
Classifier: Development Status :: 4 - Beta
Classifier: Intended Audience :: Developers
Classifier: Natural Language :: English
Classifier: Programming Language :: Python :: 3.9
Classifier: Programming Language :: Python :: 3.10
Classifier: License :: OSI Approved :: Apache Software License
Requires-Python: >=3.9
License-File: LICENSE
Requires-Dist: fastcore
Requires-Dist: torch
Requires-Dist: torchdiffeq
Requires-Dist: matplotlib
Requires-Dist: numpy
Provides-Extra: dev
Requires-Dist: nbdev ; extra == 'dev'
